studensefog/__init__.py
studensefog/tcpclientcorrespondence.py
studensefog/tcpservercorrespondence.py
stu_dense_fog-1.0.1.dist-info/LICENSE
stu_dense_fog-1.0.1.dist-info/METADATA
stu_dense_fog-1.0.1.dist-info/WHEEL
stu_dense_fog-1.0.1.dist-info/top_level.txt
stu_dense_fog-1.0.1.dist-info/RECORD
