Metadata-Version: 2.1
Name: stu-dense-fog
Version: 1.0.1
Summary: 快速架构tcp服务器并于模型交互
Author: LYX
Author-email: 1787424709@qq.com
Classifier: Programming Language :: Python :: 3
Classifier: License :: OSI Approved :: MIT License
Classifier: Operating System :: POSIX :: Linux
Classifier: Operating System :: Microsoft :: Windows
Requires-Python: >=3
License-File: LICENSE
